{
    "sourceFile": "src/components/products.jsx",
    "activeCommit": 0,
    "commits": [
        {
            "activePatchIndex": 34,
            "patches": [
                {
                    "date": 1736877635909,
                    "content": "Index: \n===================================================================\n--- \n+++ \n"
                },
                {
                    "date": 1736877730695,
                    "content": "Index: \n===================================================================\n--- \n+++ \n@@ -1,62 +1,136 @@\n import React, { useEffect, useState } from 'react';\n+import \"./products.css\"\n+import { useNavigate } from 'react-router-dom';\n \n-const Products = () => {\n \n+const Products = ({setSelectedProduct , addToCart, cart, handleShowAlert ,showAlert, searchTerm, highlightText}) => {\n \n+  \n \n     const [products, setProducts] = useState([]);\n     const [loading, setLoading] = useState(true);\n   \n+    const navigate = useNavigate();\n+// const DataContext = createContext();\n \n+  // Handle product click\n+  // const {setSelectedProduct} = useContext(DataContext)\n+ \n+  const handleProductClick = (product) => {\n+    setSelectedProduct(product);\n+    navigate(\"/selectedProduct\")\n+  };\n+\n+\n     useEffect(() => {\n         // Fetch images from the local API\n-        fetch('http://localhost:5000/products') // Adjust the URL if necessary\n+        fetch('http://localhost:5000/products?_sort=_id&_order=desc') // Adjust the URL if necessary\n             .then(response => response.json())\n             .then(data => {\n                 setProducts(data);\n                 setLoading(false);\n             })\n             .catch(error => {\n-                console.error('Error fetching images:', error);\n+                alert('could not load products');\n                 setLoading(false);\n             });\n     }, []);\n \n+   \n+\n+    \n+\n+\n+    const totalPrice = cart.reduce((total, item) => total + item.price * (item.quantity || 1), 0);\n+\n+\n+const handleAlert = () => {\n+   alert(\"allert\")\n+  \n+}\n+\n+const filteredProducts = products.filter((product) =>\n+  product.name.toLowerCase().includes(searchTerm.toLowerCase())\n+);\n+\n+const cl1 = (product) => {\n+  addToCart()\n+}\n+\n   return (\n-    <div>\n-            <h1>Imagelery</h1>\n+    <>\n+  \n+\n+    <div className='box1'>\n+            <h1></h1>\n             {loading ? (\n                 <p>Loading...</p>\n             ) : (\n-                <div style={{ display: 'flex', flexWrap: 'wrap' }} >\n-                  {products.map((product, index) => (\n+                \n+                <div style={{ display: 'flex', flexWrap: 'wrap' }}   >\n                     \n-                    <div key={products._id} style={{background:\"red\", margin:\"10px\", height:\"200px\",width:\"200px\"}}>\n+                    {/* <div>\n+                        <a className='btn btn-primary btn-sm me-1' href=\"\">\n+                            Edit\n+                        </a>\n+                        <button type='button' className='btn btn-danger btn-sm'>Delete</button>\n+                    </div> */}\n+                  {filteredProducts.map((product, index) => (\n+                    \n+                    <div key={products._id} className='box2'  >\n                        \n-                    <img\n-                        src={'http://localhost:5000/products/'+product.imageName}\n+                    <img className='image'\n+                        src={'http://localhost:5000/images/'+product.image}\n                         alt={product.name}\n-                        style={{ width: '200px', height: '150px', borderRadius: '8px' }}\n-                      \n+                        onClick={() => handleProductClick(product)}\n+                       \n                         />\n-                         <span>\n-                            <div><a>{product.name}</a></div>\n-                            <div><a>{product.desc}</a></div>\n+                         <span className='text'>\n+                            <a  className='name'><span style={{color:\"black\"}} \n+                                dangerouslySetInnerHTML={{\n+                                __html: highlightText(product.name, searchTerm),\n+                                       }}\n+                                 ></span> </a>\n+                            <a>Description: {product.desc}</a>\n+                            <a>Price: {product.price}</a>\n                          </span>\n+                         <div className='cart'>\n+                            <button className='btn btn-warning' onClick={() => } >Add to Cart</button>\n+                            \n+                         </div>\n+                          \n                          \n                     </div>\n \n-            \n                   ))}\n                   \n-         \n-        \n-                   \n+                  <button onClick={handleShowAlert}>Show Custom Alert</button>\n+      {showAlert && (\n+        <div style={{ padding: \"10px\", backgroundColor: \"red\", color: \"white\" }}>\n+          This is a custom alert!\n+        </div>\n+      )}\n+      \n+\n+            <h3>Total: ${totalPrice}</h3> \n+     \n                 </div>\n                \n             )}\n-        </div> \n+            \n+        </div > \n+        {/* <div style={{display:\"\"}}>\n+        {cart.map((item, index) => (\n+        <ProductView key={index}\n+      id={item.id} name={item.name} desc={item.desc} price={item.price} numberInStock={item.quantity}  />\n+        \n+      ))}\n+        </div> */}\n+\n+      \n+        \n+        </>\n   )\n }\n \n-export default Products\n+export default Products\n\\ No newline at end of file\n"
                },
                {
                    "date": 1736877799237,
                    "content": "Index: \n===================================================================\n--- \n+++ \n@@ -94,9 +94,9 @@\n                             <a>Description: {product.desc}</a>\n                             <a>Price: {product.price}</a>\n                          </span>\n                          <div className='cart'>\n-                            <button className='btn btn-warning' onClick={() => } >Add to Cart</button>\n+                            <button className='btn btn-warning' onClick={() => a} >Add to Cart</button>\n                             \n                          </div>\n                           \n                          \n"
                },
                {
                    "date": 1736877811279,
                    "content": "Index: \n===================================================================\n--- \n+++ \n@@ -43,11 +43,9 @@\n \n     const totalPrice = cart.reduce((total, item) => total + item.price * (item.quantity || 1), 0);\n \n \n-const handleAlert = () => {\n-   alert(\"allert\")\n-  \n+\n }\n \n const filteredProducts = products.filter((product) =>\n   product.name.toLowerCase().includes(searchTerm.toLowerCase())\n@@ -94,9 +92,9 @@\n                             <a>Description: {product.desc}</a>\n                             <a>Price: {product.price}</a>\n                          </span>\n                          <div className='cart'>\n-                            <button className='btn btn-warning' onClick={() => a} >Add to Cart</button>\n+                            <button className='btn btn-warning' onClick={() => addToCart} >Add to Cart</button>\n                             \n                          </div>\n                           \n                          \n"
                },
                {
                    "date": 1736877836023,
                    "content": "Index: \n===================================================================\n--- \n+++ \n@@ -42,20 +42,16 @@\n \n \n     const totalPrice = cart.reduce((total, item) => total + item.price * (item.quantity || 1), 0);\n \n-\n-\n }\n \n const filteredProducts = products.filter((product) =>\n   product.name.toLowerCase().includes(searchTerm.toLowerCase())\n );\n \n-const cl1 = (product) => {\n-  addToCart()\n-}\n \n+\n   return (\n     <>\n   \n \n"
                },
                {
                    "date": 1736877862151,
                    "content": "Index: \n===================================================================\n--- \n+++ \n@@ -48,10 +48,12 @@\n const filteredProducts = products.filter((product) =>\n   product.name.toLowerCase().includes(searchTerm.toLowerCase())\n );\n \n+const cl1 = (product) => {\n+  addToCart()\n+}\n \n-\n   return (\n     <>\n   \n \n"
                },
                {
                    "date": 1736877873108,
                    "content": "Index: \n===================================================================\n--- \n+++ \n@@ -42,8 +42,12 @@\n \n \n     const totalPrice = cart.reduce((total, item) => total + item.price * (item.quantity || 1), 0);\n \n+\n+const handleAlert = () => {\n+   alert(\"allert\")\n+  \n }\n \n const filteredProducts = products.filter((product) =>\n   product.name.toLowerCase().includes(searchTerm.toLowerCase())\n"
                },
                {
                    "date": 1736877882041,
                    "content": "Index: \n===================================================================\n--- \n+++ \n@@ -42,14 +42,8 @@\n \n \n     const totalPrice = cart.reduce((total, item) => total + item.price * (item.quantity || 1), 0);\n \n-\n-const handleAlert = () => {\n-   alert(\"allert\")\n-  \n-}\n-\n const filteredProducts = products.filter((product) =>\n   product.name.toLowerCase().includes(searchTerm.toLowerCase())\n );\n \n"
                },
                {
                    "date": 1736877888979,
                    "content": "Index: \n===================================================================\n--- \n+++ \n@@ -42,16 +42,15 @@\n \n \n     const totalPrice = cart.reduce((total, item) => total + item.price * (item.quantity || 1), 0);\n \n+\n const filteredProducts = products.filter((product) =>\n   product.name.toLowerCase().includes(searchTerm.toLowerCase())\n );\n \n-const cl1 = (product) => {\n-  addToCart()\n-}\n \n+\n   return (\n     <>\n   \n \n"
                },
                {
                    "date": 1736878129363,
                    "content": "Index: \n===================================================================\n--- \n+++ \n@@ -43,14 +43,21 @@\n \n     const totalPrice = cart.reduce((total, item) => total + item.price * (item.quantity || 1), 0);\n \n \n+const handleAlert = () => {\n+   alert(\"allert\")\n+  \n+}\n+\n const filteredProducts = products.filter((product) =>\n   product.name.toLowerCase().includes(searchTerm.toLowerCase())\n );\n \n+const Addtocart = (product) => {\n+  addToCart()\n+}\n \n-\n   return (\n     <>\n   \n \n@@ -87,9 +94,9 @@\n                             <a>Description: {product.desc}</a>\n                             <a>Price: {product.price}</a>\n                          </span>\n                          <div className='cart'>\n-                            <button className='btn btn-warning' onClick={() => addToCart} >Add to Cart</button>\n+                            <button className='btn btn-warning' onClick={ () => {Addtocart();handleShowAlert();}} >Add to Cart</button>\n                             \n                          </div>\n                           \n                          \n"
                },
                {
                    "date": 1736878156527,
                    "content": "Index: \n===================================================================\n--- \n+++ \n@@ -94,9 +94,9 @@\n                             <a>Description: {product.desc}</a>\n                             <a>Price: {product.price}</a>\n                          </span>\n                          <div className='cart'>\n-                            <button className='btn btn-warning' onClick={ () => {Addtocart();handleShowAlert();}} >Add to Cart</button>\n+                            <button className='btn btn-warning' onClick={ () => {Addtocart()} >Add to Cart</button>\n                             \n                          </div>\n                           \n                          \n"
                },
                {
                    "date": 1736878163796,
                    "content": "Index: \n===================================================================\n--- \n+++ \n@@ -94,9 +94,9 @@\n                             <a>Description: {product.desc}</a>\n                             <a>Price: {product.price}</a>\n                          </span>\n                          <div className='cart'>\n-                            <button className='btn btn-warning' onClick={ () => {Addtocart()} >Add to Cart</button>\n+                            <button className='btn btn-warning' onClick={ () => Addtocart()} >Add to Cart</button>\n                             \n                          </div>\n                           \n                          \n"
                },
                {
                    "date": 1736878185420,
                    "content": "Index: \n===================================================================\n--- \n+++ \n@@ -52,12 +52,10 @@\n const filteredProducts = products.filter((product) =>\n   product.name.toLowerCase().includes(searchTerm.toLowerCase())\n );\n \n-const Addtocart = (product) => {\n-  addToCart()\n-}\n \n+\n   return (\n     <>\n   \n \n"
                },
                {
                    "date": 1736878342756,
                    "content": "Index: \n===================================================================\n--- \n+++ \n@@ -92,9 +92,9 @@\n                             <a>Description: {product.desc}</a>\n                             <a>Price: {product.price}</a>\n                          </span>\n                          <div className='cart'>\n-                            <button className='btn btn-warning' onClick={ () => Addtocart()} >Add to Cart</button>\n+                            <button className='btn btn-warning' onClick={ () => ddtocart()} >Add to Cart</button>\n                             \n                          </div>\n                           \n                          \n"
                },
                {
                    "date": 1736878349472,
                    "content": "Index: \n===================================================================\n--- \n+++ \n@@ -92,9 +92,9 @@\n                             <a>Description: {product.desc}</a>\n                             <a>Price: {product.price}</a>\n                          </span>\n                          <div className='cart'>\n-                            <button className='btn btn-warning' onClick={ () => ddtocart()} >Add to Cart</button>\n+                            <button className='btn btn-warning' onClick={ () => addToCartddtocart()} >Add to Cart</button>\n                             \n                          </div>\n                           \n                          \n"
                },
                {
                    "date": 1736878355932,
                    "content": "Index: \n===================================================================\n--- \n+++ \n@@ -92,9 +92,9 @@\n                             <a>Description: {product.desc}</a>\n                             <a>Price: {product.price}</a>\n                          </span>\n                          <div className='cart'>\n-                            <button className='btn btn-warning' onClick={ () => addToCartddtocart()} >Add to Cart</button>\n+                            <button className='btn btn-warning' onClick={ () => addToCartd()} >Add to Cart</button>\n                             \n                          </div>\n                           \n                          \n"
                },
                {
                    "date": 1736878384092,
                    "content": "Index: \n===================================================================\n--- \n+++ \n@@ -0,0 +1,134 @@\n+import React, { useEffect, useState } from 'react';\n+import \"./products.css\"\n+import { useNavigate } from 'react-router-dom';\n+\n+\n+const Products = ({setSelectedProduct , addToCart, cart, handleShowAlert ,showAlert, searchTerm, highlightText}) => {\n+\n+  \n+\n+    const [products, setProducts] = useState([]);\n+    const [loading, setLoading] = useState(true);\n+  \n+    const navigate = useNavigate();\n+// const DataContext = createContext();\n+\n+  // Handle product click\n+  // const {setSelectedProduct} = useContext(DataContext)\n+ \n+  const handleProductClick = (product) => {\n+    setSelectedProduct(product);\n+    navigate(\"/selectedProduct\")\n+  };\n+\n+\n+    useEffect(() => {\n+        // Fetch images from the local API\n+        fetch('http://localhost:5000/products?_sort=_id&_order=desc') // Adjust the URL if necessary\n+            .then(response => response.json())\n+            .then(data => {\n+                setProducts(data);\n+                setLoading(false);\n+            })\n+            .catch(error => {\n+                alert('could not load products');\n+                setLoading(false);\n+            });\n+    }, []);\n+\n+   \n+\n+    \n+\n+\n+    const totalPrice = cart.reduce((total, item) => total + item.price * (item.quantity || 1), 0);\n+\n+\n+const handleAlert = () => {\n+   alert(\"allert\")\n+  \n+}\n+\n+const filteredProducts = products.filter((product) =>\n+  product.name.toLowerCase().includes(searchTerm.toLowerCase())\n+);\n+\n+\n+\n+  return (\n+    <>\n+  \n+\n+    <div className='box1'>\n+            <h1></h1>\n+            {loading ? (\n+                <p>Loading...</p>\n+            ) : (\n+                \n+                <div style={{ display: 'flex', flexWrap: 'wrap' }}   >\n+                    \n+                    {/* <div>\n+                        <a className='btn btn-primary btn-sm me-1' href=\"\">\n+                            Edit\n+                        </a>\n+                        <button type='button' className='btn btn-danger btn-sm'>Delete</button>\n+                    </div> */}\n+                  {filteredProducts.map((product, index) => (\n+                    \n+                    <div key={products._id} className='box2'  >\n+                       \n+                    <img className='image'\n+                        src={'http://localhost:5000/images/'+product.image}\n+                        alt={product.name}\n+                        onClick={() => handleProductClick(product)}\n+                       \n+                        />\n+                         <span className='text'>\n+                            <a  className='name'><span style={{color:\"black\"}} \n+                                dangerouslySetInnerHTML={{\n+                                __html: highlightText(product.name, searchTerm),\n+                                       }}\n+                                 ></span> </a>\n+                            <a>Description: {product.desc}</a>\n+                            <a>Price: {product.price}</a>\n+                         </span>\n+                         <div className='cart'>\n+                            <button className='btn btn-warning' onClick={ () => addToCart} >Add to Cart</button>\n+                            \n+                         </div>\n+                          \n+                         \n+                    </div>\n+\n+                  ))}\n+                  \n+                  <button onClick={handleShowAlert}>Show Custom Alert</button>\n+      {showAlert && (\n+        <div style={{ padding: \"10px\", backgroundColor: \"red\", color: \"white\" }}>\n+          This is a custom alert!\n+        </div>\n+      )}\n+      \n+\n+            <h3>Total: ${totalPrice}</h3> \n+     \n+                </div>\n+               \n+            )}\n+            \n+        </div > \n+        {/* <div style={{display:\"\"}}>\n+        {cart.map((item, index) => (\n+        <ProductView key={index}\n+      id={item.id} name={item.name} desc={item.desc} price={item.price} numberInStock={item.quantity}  />\n+        \n+      ))}\n+        </div> */}\n+\n+      \n+        \n+        </>\n+  )\n+}\n+\n+export default Products\n\\ No newline at end of file\n"
                },
                {
                    "date": 1736878394086,
                    "content": "Index: \n===================================================================\n--- \n+++ \n@@ -92,9 +92,9 @@\n                             <a>Description: {product.desc}</a>\n                             <a>Price: {product.price}</a>\n                          </span>\n                          <div className='cart'>\n-                            <button className='btn btn-warning' onClick={ () => addToCart} >Add to Cart</button>\n+                            <button className='btn btn-warning' onClick={ () => addToCart()} >Add to Cart</button>\n                             \n                          </div>\n                           \n                          \n@@ -130,139 +130,5 @@\n         </>\n   )\n }\n \n-export default Products\n-import React, { useEffect, useState } from 'react';\n-import \"./products.css\"\n-import { useNavigate } from 'react-router-dom';\n-\n-\n-const Products = ({setSelectedProduct , addToCart, cart, handleShowAlert ,showAlert, searchTerm, highlightText}) => {\n-\n-  \n-\n-    const [products, setProducts] = useState([]);\n-    const [loading, setLoading] = useState(true);\n-  \n-    const navigate = useNavigate();\n-// const DataContext = createContext();\n-\n-  // Handle product click\n-  // const {setSelectedProduct} = useContext(DataContext)\n- \n-  const handleProductClick = (product) => {\n-    setSelectedProduct(product);\n-    navigate(\"/selectedProduct\")\n-  };\n-\n-\n-    useEffect(() => {\n-        // Fetch images from the local API\n-        fetch('http://localhost:5000/products?_sort=_id&_order=desc') // Adjust the URL if necessary\n-            .then(response => response.json())\n-            .then(data => {\n-                setProducts(data);\n-                setLoading(false);\n-            })\n-            .catch(error => {\n-                alert('could not load products');\n-                setLoading(false);\n-            });\n-    }, []);\n-\n-   \n-\n-    \n-\n-\n-    const totalPrice = cart.reduce((total, item) => total + item.price * (item.quantity || 1), 0);\n-\n-\n-const handleAlert = () => {\n-   alert(\"allert\")\n-  \n-}\n-\n-const filteredProducts = products.filter((product) =>\n-  product.name.toLowerCase().includes(searchTerm.toLowerCase())\n-);\n-\n-\n-\n-  return (\n-    <>\n-  \n-\n-    <div className='box1'>\n-            <h1></h1>\n-            {loading ? (\n-                <p>Loading...</p>\n-            ) : (\n-                \n-                <div style={{ display: 'flex', flexWrap: 'wrap' }}   >\n-                    \n-                    {/* <div>\n-                        <a className='btn btn-primary btn-sm me-1' href=\"\">\n-                            Edit\n-                        </a>\n-                        <button type='button' className='btn btn-danger btn-sm'>Delete</button>\n-                    </div> */}\n-                  {filteredProducts.map((product, index) => (\n-                    \n-                    <div key={products._id} className='box2'  >\n-                       \n-                    <img className='image'\n-                        src={'http://localhost:5000/images/'+product.image}\n-                        alt={product.name}\n-                        onClick={() => handleProductClick(product)}\n-                       \n-                        />\n-                         <span className='text'>\n-                            <a  className='name'><span style={{color:\"black\"}} \n-                                dangerouslySetInnerHTML={{\n-                                __html: highlightText(product.name, searchTerm),\n-                                       }}\n-                                 ></span> </a>\n-                            <a>Description: {product.desc}</a>\n-                            <a>Price: {product.price}</a>\n-                         </span>\n-                         <div className='cart'>\n-                            <button className='btn btn-warning' onClick={ () => addToCartd()} >Add to Cart</button>\n-                            \n-                         </div>\n-                          \n-                         \n-                    </div>\n-\n-                  ))}\n-                  \n-                  <button onClick={handleShowAlert}>Show Custom Alert</button>\n-      {showAlert && (\n-        <div style={{ padding: \"10px\", backgroundColor: \"red\", color: \"white\" }}>\n-          This is a custom alert!\n-        </div>\n-      )}\n-      \n-\n-            <h3>Total: ${totalPrice}</h3> \n-     \n-                </div>\n-               \n-            )}\n-            \n-        </div > \n-        {/* <div style={{display:\"\"}}>\n-        {cart.map((item, index) => (\n-        <ProductView key={index}\n-      id={item.id} name={item.name} desc={item.desc} price={item.price} numberInStock={item.quantity}  />\n-        \n-      ))}\n-        </div> */}\n-\n-      \n-        \n-        </>\n-  )\n-}\n-\n export default Products\n\\ No newline at end of file\n"
                },
                {
                    "date": 1736934586989,
                    "content": "Index: \n===================================================================\n--- \n+++ \n@@ -49,9 +49,9 @@\n   \n }\n \n const filteredProducts = products.filter((product) =>\n-  product.name.toLowerCase().includes(searchTerm.toLowerCase())\n+  product.name .toLowerCase().includes(searchTerm.toLowerCase())\n );\n \n \n \n"
                },
                {
                    "date": 1736934592703,
                    "content": "Index: \n===================================================================\n--- \n+++ \n@@ -49,9 +49,9 @@\n   \n }\n \n const filteredProducts = products.filter((product) =>\n-  product.name .toLowerCase().includes(searchTerm.toLowerCase())\n+  product.name || .toLowerCase().includes(searchTerm.toLowerCase())\n );\n \n \n \n"
                },
                {
                    "date": 1736934599552,
                    "content": "Index: \n===================================================================\n--- \n+++ \n@@ -49,9 +49,9 @@\n   \n }\n \n const filteredProducts = products.filter((product) =>\n-  product.name || .toLowerCase().includes(searchTerm.toLowerCase())\n+  product.name || product.toLowerCase().includes(searchTerm.toLowerCase())\n );\n \n \n \n"
                },
                {
                    "date": 1736934606953,
                    "content": "Index: \n===================================================================\n--- \n+++ \n@@ -49,9 +49,9 @@\n   \n }\n \n const filteredProducts = products.filter((product) =>\n-  product.name || product.toLowerCase().includes(searchTerm.toLowerCase())\n+  product.name || product.categoty.toLowerCase().includes(searchTerm.toLowerCase())\n );\n \n \n \n"
                },
                {
                    "date": 1736934613550,
                    "content": "Index: \n===================================================================\n--- \n+++ \n@@ -49,9 +49,9 @@\n   \n }\n \n const filteredProducts = products.filter((product) =>\n-  product.name || product.categoty.toLowerCase().includes(searchTerm.toLowerCase())\n+  product.name || product.category.toLowerCase().includes(searchTerm.toLowerCase())\n );\n \n \n \n"
                },
                {
                    "date": 1736934780354,
                    "content": "Index: \n===================================================================\n--- \n+++ \n@@ -49,9 +49,9 @@\n   \n }\n \n const filteredProducts = products.filter((product) =>\n-  product.name || product.category.toLowerCase().includes(searchTerm.toLowerCase())\n+  product.name | product.category.toLowerCase().includes(searchTerm.toLowerCase())\n );\n \n \n \n"
                },
                {
                    "date": 1736934836508,
                    "content": "Index: \n===================================================================\n--- \n+++ \n@@ -49,9 +49,9 @@\n   \n }\n \n const filteredProducts = products.filter((product) =>\n-  product.name | product.category.toLowerCase().includes(searchTerm.toLowerCase())\n+  product.name  product.category.toLowerCase().includes(searchTerm.toLowerCase())\n );\n \n \n \n"
                },
                {
                    "date": 1736934847312,
                    "content": "Index: \n===================================================================\n--- \n+++ \n@@ -50,8 +50,9 @@\n }\n \n const filteredProducts = products.filter((product) =>\n   product.name  product.category.toLowerCase().includes(searchTerm.toLowerCase())\n+\n );\n \n \n \n"
                },
                {
                    "date": 1736934854669,
                    "content": "Index: \n===================================================================\n--- \n+++ \n@@ -49,10 +49,10 @@\n   \n }\n \n const filteredProducts = products.filter((product) =>\n-  product.name  product.category.toLowerCase().includes(searchTerm.toLowerCase())\n-\n+  product.name .toLowerCase().includes(searchTerm.toLowerCase())\n+product.category.toLowerCase().includes(searchTerm.toLowerCase())\n );\n \n \n \n"
                },
                {
                    "date": 1736934861416,
                    "content": "Index: \n===================================================================\n--- \n+++ \n@@ -49,9 +49,9 @@\n   \n }\n \n const filteredProducts = products.filter((product) =>\n-  product.name .toLowerCase().includes(searchTerm.toLowerCase())\n+  product.name .toLowerCase().includes(searchTerm.toLowerCase()),\n product.category.toLowerCase().includes(searchTerm.toLowerCase())\n );\n \n \n"
                },
                {
                    "date": 1736934878988,
                    "content": "Index: \n===================================================================\n--- \n+++ \n@@ -50,9 +50,9 @@\n }\n \n const filteredProducts = products.filter((product) =>\n   product.name .toLowerCase().includes(searchTerm.toLowerCase()),\n-product.category.toLowerCase().includes(searchTerm.toLowerCase())\n+   product.category.toLowerCase().includes(searchTerm.toLowerCase())\n );\n \n \n \n"
                },
                {
                    "date": 1736934893787,
                    "content": "Index: \n===================================================================\n--- \n+++ \n@@ -48,11 +48,11 @@\n    alert(\"allert\")\n   \n }\n \n-const filteredProducts = products.filter((product) =>\n+const filteredProducts = products.filter((product) => \n   product.name .toLowerCase().includes(searchTerm.toLowerCase()),\n-   product.category.toLowerCase().includes(searchTerm.toLowerCase())\n+  product.category.toLowerCase().includes(searchTerm.toLowerCase())\n );\n \n \n \n"
                },
                {
                    "date": 1736934901661,
                    "content": "Index: \n===================================================================\n--- \n+++ \n@@ -48,11 +48,11 @@\n    alert(\"allert\")\n   \n }\n \n-const filteredProducts = products.filter((product) => \n+const filteredProducts = products.filter((product) => {\n   product.name .toLowerCase().includes(searchTerm.toLowerCase()),\n-  product.category.toLowerCase().includes(searchTerm.toLowerCase())\n+  product.category.toLowerCase().includes(searchTerm.toLowerCase())}\n );\n \n \n \n"
                },
                {
                    "date": 1736934913324,
                    "content": "Index: \n===================================================================\n--- \n+++ \n@@ -50,9 +50,9 @@\n }\n \n const filteredProducts = products.filter((product) => {\n   product.name .toLowerCase().includes(searchTerm.toLowerCase()),\n-  product.category.toLowerCase().includes(searchTerm.toLowerCase())}\n+  product.category.toLowerCase().includes(searchTerm.toLowerCase())\n );\n \n \n \n"
                },
                {
                    "date": 1736934918593,
                    "content": "Index: \n===================================================================\n--- \n+++ \n@@ -48,11 +48,11 @@\n    alert(\"allert\")\n   \n }\n \n-const filteredProducts = products.filter((product) => {\n+const filteredProducts = products.filter((product) => ()\n   product.name .toLowerCase().includes(searchTerm.toLowerCase()),\n-  product.category.toLowerCase().includes(searchTerm.toLowerCase())\n+  product.category.toLowerCase().includes(searchTerm.toLowerCase()))\n );\n \n \n \n"
                },
                {
                    "date": 1736934995514,
                    "content": "Index: \n===================================================================\n--- \n+++ \n@@ -49,9 +49,9 @@\n   \n }\n \n const filteredProducts = products.filter((product) => (\n-  product.name .toLowerCase().includes(searchTerm.toLowerCase())\n+  product.name .toLowerCase().includes(searchTerm.toLowerCase()) \n   product.category.toLowerCase().includes(searchTerm.toLowerCase()))\n );\n \n \n"
                },
                {
                    "date": 1736937325724,
                    "content": "Index: \n===================================================================\n--- \n+++ \n@@ -16,10 +16,8 @@\n   // Handle product click\n   // const {setSelectedProduct} = useContext(DataContext)\n  \n \n-\n-\n     useEffect(() => {\n         // Fetch images from the local API\n         fetch('http://localhost:5000/products?_sort=_id&_order=desc') // Adjust the URL if necessary\n             .then(response => response.json())\n"
                }
            ],
            "date": 1736877635909,
            "name": "Commit-0",
            "content": "import React, { useEffect, useState } from 'react';\n\nconst Products = () => {\n\n\n\n    const [products, setProducts] = useState([]);\n    const [loading, setLoading] = useState(true);\n  \n\n    useEffect(() => {\n        // Fetch images from the local API\n        fetch('http://localhost:5000/products') // Adjust the URL if necessary\n            .then(response => response.json())\n            .then(data => {\n                setProducts(data);\n                setLoading(false);\n            })\n            .catch(error => {\n                console.error('Error fetching images:', error);\n                setLoading(false);\n            });\n    }, []);\n\n  return (\n    <div>\n            <h1>Imagelery</h1>\n            {loading ? (\n                <p>Loading...</p>\n            ) : (\n                <div style={{ display: 'flex', flexWrap: 'wrap' }} >\n                  {products.map((product, index) => (\n                    \n                    <div key={products._id} style={{background:\"red\", margin:\"10px\", height:\"200px\",width:\"200px\"}}>\n                       \n                    <img\n                        src={'http://localhost:5000/products/'+product.imageName}\n                        alt={product.name}\n                        style={{ width: '200px', height: '150px', borderRadius: '8px' }}\n                      \n                        />\n                         <span>\n                            <div><a>{product.name}</a></div>\n                            <div><a>{product.desc}</a></div>\n                         </span>\n                         \n                    </div>\n\n            \n                  ))}\n                  \n         \n        \n                   \n                </div>\n               \n            )}\n        </div> \n  )\n}\n\nexport default Products\n"
        }
    ]
}